{"basics":{"name":"Francisco G. Pena","label":"Software Engineer","image":"","email":"franciscogupe@gmail.com","phone":"","url":"","summary":""},"work":[{"name":"Amazon","position":"Software Engineer","url":"","startDate":"2023-11-21","endDate":"NOW","summary":"Development, documentation and maintenance of backend systems, deployed to AWS, which manage Amazon global invoicing system with Java and Python.","highlights":["Java","Python","AWS"]},{"name":"Copybase","position":"BUILDING..."}],"languages":[{"language":"Portuguese","fluency":"Native speaker","icon":""},{"language":"English","fluency":"Fluent","icon":""},{"language":"Spanish","fluency":"advanced","icon":""}]}